orion/VERSION
orion/__about__.py
orion/__init__.py
orion/__main__.py
orion/_pyinstaller/__init__.py
orion/_pyinstaller/hook-csep.py
orion/_pyinstaller/hook-orion.py
orion/_pyinstaller/hook-rasterio.py
orion/_pyinstaller/hook-xyzservices.py
orion/_pyinstaller/orion_logo.png
orion/_pyinstaller/run-orion.py
orion/examples/__init__.py
orion/examples/built_in_manager.py
orion/examples/update_config_files.py
orion/external_database/__init__.py
orion/external_database/california_doggr.py
orion/external_database/oklahoma_corporation_commission.py
orion/external_database/texas_railroad_commission.py
orion/forecast_models/__init__.py
orion/forecast_models/coupled_coulomb_rate_state_model.py
orion/forecast_models/etas_model.py
orion/forecast_models/forecast_model_base.py
orion/forecast_models/openSHA_model.py
orion/forecast_models/pretrained_lstm_model.py
orion/forecast_models/reasenberg_jones_model.py
orion/forecast_models/seismogenic_index_model.py
orion/forecast_models/rate_and_state_ode_model/__init__.py
orion/forecast_models/rate_and_state_ode_model/_common.py
orion/forecast_models/rate_and_state_ode_model/_helpers.py
orion/forecast_models/rate_and_state_ode_model/_rsode_model.py
orion/gui/__init__.py
orion/gui/about_gui.py
orion/gui/config_gui.py
orion/gui/custom_widgets.py
orion/gui/example_download_gui.py
orion/gui/gui_api.py
orion/gui/gui_base.py
orion/gui/gui_element_factory.py
orion/gui/lbnl.png
orion/gui/llnl.png
orion/gui/logos_all.png
orion/gui/nrap.png
orion/gui/orion_gui.py
orion/gui/orion_logo.png
orion/gui/orion_logo_simple.png
orion/gui/orion_strive.py
orion/gui/quickstart_wizard.py
orion/gui/smart.png
orion/gui/smart_orb.png
orion/gui/wizard_base.py
orion/managers/__init__.py
orion/managers/appearance_manager.py
orion/managers/catalog_overview_manager.py
orion/managers/data_manager_base.py
orion/managers/forecast_manager.py
orion/managers/geologic_model_manager.py
orion/managers/grid_manager.py
orion/managers/manager_base.py
orion/managers/orion_manager.py
orion_seismic_forecast-0.5.3.dist-info/LICENSE
orion_seismic_forecast-0.5.3.dist-info/METADATA
orion_seismic_forecast-0.5.3.dist-info/NOTICE
orion_seismic_forecast-0.5.3.dist-info/WHEEL
orion_seismic_forecast-0.5.3.dist-info/entry_points.txt
orion_seismic_forecast-0.5.3.dist-info/top_level.txt
orion_seismic_forecast-0.5.3.dist-info/RECORD
